{
  "model": "UQ_T1_traffic_only",
  "horizon": 6,
  "seed": 20260623,
  "feature_count": 25,
  "encoded_feature_count": 77,
  "train_samples": 68717,
  "tuning_samples": 7468,
  "calibration_samples": 6616,
  "test_samples": 13387,
  "best_iteration": 699,
  "best_tuning_quantile_loss": 0.3330471461714164,
  "elapsed_seconds": 8.998994588851929,
  "test_used_for_model_selection": false,
  "checkpoint": "09_E7_UQ\\best_checkpoint\\UQ_T1_traffic_only_h6_seed20260623.json",
  "checkpoint_sha256": "4da535e2597a55aec67a16981987de27dd248224c545eebe288cf2a5ad051739"
}